{
  "class": 4,
  "name": [
    "Theophilactus, Bishop of Nicomedia"
  ],
  "type": [
    "venerable father and confessor"
  ],
  "saint": [
    "Our"
  ],
  "troparia": [
    "<i>(Tone 6)</i> You tried to live a hidden life, O praiseworthy father,* but Christ made you a lamp upon the light of thought.* He handed you the tablets of spiritual knowledge.* Enlighten us by the, O holy Theophilactus."
  ],
  "kontakia": [
    "<i>(Tone 2)</i> You became a lamp for the whole world, O father,* and by preaching that the Word had the nature common to the Father and the Spirit,* you enlightened the Council of heavenly fathers.* You became a defender of the Trinity.* As you stand before them, pray unceasingly for all of us."
  ]
}