{
  "note on sources": "The rubric from Monday 1st hour in Triodion suggests that we should do veneration of the Cross at the 1st hour instead of Стопы моя on Mon, Wen and Fri. But Dolnytsky at pages 410-411 basically tells not to do it that way, and to have veneration every day after every service.",
  "troparion": "<i>(Tone 7)</i> In your wrath, O Lord,* do not chastise the people who have sinned against You,* nor find fault with them in Your anger;* for You are the God of goodness.* All the earth glorifies You, and we pray to You:* Spare us, O holy One.",
  "prokimenon": [
    "6 (Ps. 61)",
    "In God* is my safety",
    "and glory.",
    "In God alone is my soul at rest."
  ],
  "readings": [
    "Isaiah 14:24-32"
  ],
  "second_prokimenon": [
    "4 (Ps. 62)",
    "So I will bless You",
    "all my life.",
    " O God, You are my God, for You I long; for You my soul is thirsting."
  ]
}